combss/.DS_Store
combss/__init__.py
combss/_opt_lm.py
combss/linear.py
combss/metrics.py
combss-1.1.4.dist-info/licenses/LICENSE
combss-1.1.4.dist-info/WHEEL
combss-1.1.4.dist-info/METADATA
combss-1.1.4.dist-info/RECORD
