Metadata-Version: 2.4
Name: combss
Version: 1.1.4
Summary: A package implementation of COMBSS, a continuous optimisation method toward best subset selection
Keywords: mathematics,optimization,subset selection
Author: Sarat Moka, Hua Yang Hu
Classifier: License :: OSI Approved :: Apache Software License
Classifier: Programming Language :: Python :: 3
Classifier: Operating System :: OS Independent
Classifier: Topic :: Scientific/Engineering :: Mathematics
License-File: LICENSE
Requires-Dist: numpy>=1.21.0
Requires-Dist: scipy>=1.7.0
